sunsunsunTest/test1.py
sunsunsunTest/test2.py
sunsunsunTest-0.0.0.1.dist-info/METADATA
sunsunsunTest-0.0.0.1.dist-info/WHEEL
sunsunsunTest-0.0.0.1.dist-info/top_level.txt
sunsunsunTest-0.0.0.1.dist-info/RECORD
