Metadata-Version: 2.1
Name: sunsunsunTest
Version: 0.0.0.1
Summary: My First Test Package
Home-page: https://lingua.blog.me/…
Author: Soonho Lim
Author-email: lsh2716@naver.com
License: MIT
Requires-Python: >=3
